opta_api/__init__.py
opta_api/metadata.py
opta_api/optaAPI.py
opta_api/transformers.py
opta_api-0.0.5.dist-info/LICENSE
opta_api-0.0.5.dist-info/METADATA
opta_api-0.0.5.dist-info/WHEEL
opta_api-0.0.5.dist-info/top_level.txt
opta_api-0.0.5.dist-info/RECORD
